mcp_data_analyse/__init__.py
mcp_data_analyse/__main__.py
mcp_data_analyse/cli.py
mcp_data_analyse/core.py
mcp_data_analyse/my_tools.py
data_analyse_test-0.1.3.dist-info/METADATA
data_analyse_test-0.1.3.dist-info/WHEEL
data_analyse_test-0.1.3.dist-info/entry_points.txt
data_analyse_test-0.1.3.dist-info/top_level.txt
data_analyse_test-0.1.3.dist-info/RECORD
