Metadata-Version: 2.4
Name: data-analyse-test
Version: 0.1.3
Summary: 数据分析助手
Requires-Python: >=3.13
Requires-Dist: matplotlib>=3.10.5
Requires-Dist: mcp[cli]>=1.13.0
Requires-Dist: openpyxl>=3.1.5
Requires-Dist: pandas>=2.3.1
Requires-Dist: paramiko>=4.0.0
Requires-Dist: twine>=6.1.0
Requires-Dist: xlrd>=2.0.2
